pySerialForAt
