Metadata-Version: 2.1
Name: pySerialForAt
Version: 0.3
Summary: 串口forAT
Home-page: https://gitee.com/bc-y/py-serial-for-atp
Author: bc-y,w-8
Author-email: mdzzdyxc@163.com
License: MIT
Platform: UNKNOWN
Classifier: Programming Language :: Python :: 3
Classifier: License :: OSI Approved :: MIT License
Classifier: Operating System :: OS Independent
License-File: LICENSE
